quicklearn/__init__.py
quicklearn/_version.py
quicklearn/algorithms/__init__.py
quicklearn/algorithms/dnn_logger.py
quicklearn/algorithms/svm_logger.py
quicklearn/algorithms/train_dnn.py
quicklearn/algorithms/train_svm.py
quicklearn/algorithms/train_xgboost.py
quicklearn/algorithms/xgboost_logger.py
quicklearn/components/__init__.py
quicklearn/components/event_categorization.py
quicklearn/utils/__init__.py
quicklearn/utils/data_preparation.py
quicklearn/utils/gather_results.py
quicklearn/visualization/__init__.py
quicklearn/visualization/grid_plot.py
quicklearn/visualization/plot_AUC_vs_N_event.py
quicklearn/visualization/plot_with_luck.py
quicklearn/visualization/to_latex.py
quicklearn-0.1.6.data/scripts/quickTrain
quicklearn-0.1.6.dist-info/METADATA
quicklearn-0.1.6.dist-info/WHEEL
quicklearn-0.1.6.dist-info/top_level.txt
quicklearn-0.1.6.dist-info/RECORD
